Metadata-Version: 2.4
Name: llama-index-vector-stores-hnswlib
Version: 0.4.1
Summary: llama-index vector_stores hnswlib integration
Author-email: Artur Stopa <arturstopa10@gmail.com>
License-Expression: MIT
License-File: LICENSE
Requires-Python: <4.0,>=3.9
Requires-Dist: hnswlib<0.9,>=0.8.0
Requires-Dist: llama-index-core<0.15,>=0.13.0
